{"series":{"id":"cao-vo-ha-canh-en-mot-van-nam-sau-893sqz","title":"Cao Võ: Hạ Cánh Đến Một Vạn Năm Sau","aliases":[],"slug":"cao-vo-ha-canh-en-mot-van-nam-sau","coverUrl":"https://truyenqqko.com/img/w86qIN4Rb19I9y_kGezG_QNLbGo0f_fTFsovNKlZwc4/rs:fit:600:800/aHR0cDovL25naW54L2Nkbi9lYm9vay9vcmlnbmFsL2Nhby12by1oYS1jYW5oLWRlbi1tb3QtdmFuLW5hbS1zYXVfMTY3NDgxMDA0MC5qcGc_Z3Q9aGRmZ2RmZyZtb2JpbGU9Mg","thumbnailUrl":"https://s3.vn-hcm-1.vietnix.cloud/cuontruyen/imports/cao-vo-ha-canh-en-mot-van-nam-sau-893sqz/_cover/cover.webp","coverThumbnail":{"sourceUrl":"https://truyenqqko.com/img/w86qIN4Rb19I9y_kGezG_QNLbGo0f_fTFsovNKlZwc4/rs:fit:600:800/aHR0cDovL25naW54L2Nkbi9lYm9vay9vcmlnbmFsL2Nhby12by1oYS1jYW5oLWRlbi1tb3QtdmFuLW5hbS1zYXVfMTY3NDgxMDA0MC5qcGc_Z3Q9aGRmZ2RmZyZtb2JpbGU9Mg","sourceType":"source-cover","width":250,"height":331,"sourceBytes":18698,"storedBytes":17162,"format":"webp"},"description":"","status":"public","sourceMappings":[{"adapter":"truyenqq","sourceUrl":"https://truyenqqko.com/truyen-tranh/cao-vo-ha-canh-den-mot-van-nam-sau-13646"}],"tags":[],"stats":{"views":0,"follows":0,"readDepth":0,"adViews":0,"donateClicks":0},"crawlSchedule":{"enabled":false,"intervalHours":24},"importedAt":"2026-06-04T05:23:21.042Z","updatedAt":"2026-06-04T09:41:09.700Z","chapterCount":338,"importedChapterCount":338,"pageCount":12970,"chapters":[{"id":"oc-tu-au-1","title":"Đọc từ đầu","label":"Đọc từ đầu","slug":"oc-tu-au","status":"public","imported":true,"pageCount":38,"sourceOrder":0},{"id":"chuong-1-2","title":"Chương 1","label":"Chương 1","slug":"chuong-1","status":"public","imported":true,"pageCount":10,"sourceOrder":1},{"id":"chuong-1-1-3","title":"Chương 1.1","label":"Chương 1.1","slug":"chuong-1-1","status":"public","imported":true,"pageCount":113,"sourceOrder":2},{"id":"chuong-2-4","title":"Chương 2","label":"Chương 2","slug":"chuong-2","status":"public","imported":true,"pageCount":59,"sourceOrder":3},{"id":"chuong-3-5","title":"Chương 3","label":"Chương 3","slug":"chuong-3","status":"public","imported":true,"pageCount":50,"sourceOrder":4},{"id":"chuong-4-6","title":"Chương 4","label":"Chương 4","slug":"chuong-4","status":"public","imported":true,"pageCount":57,"sourceOrder":5},{"id":"chuong-5-7","title":"Chương 5","label":"Chương 5","slug":"chuong-5","status":"public","imported":true,"pageCount":44,"sourceOrder":6},{"id":"chuong-6-8","title":"Chương 6","label":"Chương 6","slug":"chuong-6","status":"public","imported":true,"pageCount":44,"sourceOrder":7},{"id":"chuong-7-9","title":"Chương 7","label":"Chương 7","slug":"chuong-7","status":"public","imported":true,"pageCount":45,"sourceOrder":8},{"id":"chuong-8-10","title":"Chương 8","label":"Chương 8","slug":"chuong-8","status":"public","imported":true,"pageCount":44,"sourceOrder":9},{"id":"chuong-9-11","title":"Chương 9","label":"Chương 9","slug":"chuong-9","status":"public","imported":true,"pageCount":60,"sourceOrder":10},{"id":"chuong-10-12","title":"Chương 10","label":"Chương 10","slug":"chuong-10","status":"public","imported":true,"pageCount":20,"sourceOrder":11},{"id":"chuong-10-5-13","title":"Chương 10.5","label":"Chương 10.5","slug":"chuong-10-5","status":"public","imported":true,"pageCount":20,"sourceOrder":12},{"id":"chuong-11-14","title":"Chương 11","label":"Chương 11","slug":"chuong-11","status":"public","imported":true,"pageCount":20,"sourceOrder":13},{"id":"chuong-11-5-15","title":"Chương 11.5","label":"Chương 11.5","slug":"chuong-11-5","status":"public","imported":true,"pageCount":20,"sourceOrder":14},{"id":"chuong-12-16","title":"Chương 12","label":"Chương 12","slug":"chuong-12","status":"public","imported":true,"pageCount":20,"sourceOrder":15},{"id":"chuong-12-5-17","title":"Chương 12.5","label":"Chương 12.5","slug":"chuong-12-5","status":"public","imported":true,"pageCount":20,"sourceOrder":16},{"id":"chuong-13-18","title":"Chương 13","label":"Chương 13","slug":"chuong-13","status":"public","imported":true,"pageCount":20,"sourceOrder":17},{"id":"chuong-13-5-19","title":"Chương 13.5","label":"Chương 13.5","slug":"chuong-13-5","status":"public","imported":true,"pageCount":20,"sourceOrder":18},{"id":"chuong-14-20","title":"Chương 14","label":"Chương 14","slug":"chuong-14","status":"public","imported":true,"pageCount":20,"sourceOrder":19},{"id":"chuong-14-5-21","title":"Chương 14.5","label":"Chương 14.5","slug":"chuong-14-5","status":"public","imported":true,"pageCount":20,"sourceOrder":20},{"id":"chuong-15-22","title":"Chương 15","label":"Chương 15","slug":"chuong-15","status":"public","imported":true,"pageCount":45,"sourceOrder":21},{"id":"chuong-16-23","title":"Chương 16","label":"Chương 16","slug":"chuong-16","status":"public","imported":true,"pageCount":33,"sourceOrder":22},{"id":"chuong-17-24","title":"Chương 17","label":"Chương 17","slug":"chuong-17","status":"public","imported":true,"pageCount":19,"sourceOrder":23},{"id":"chuong-17-5-25","title":"Chương 17.5","label":"Chương 17.5","slug":"chuong-17-5","status":"public","imported":true,"pageCount":16,"sourceOrder":24},{"id":"chuong-18-26","title":"Chương 18","label":"Chương 18","slug":"chuong-18","status":"public","imported":true,"pageCount":20,"sourceOrder":25},{"id":"chuong-18-5-27","title":"Chương 18.5","label":"Chương 18.5","slug":"chuong-18-5","status":"public","imported":true,"pageCount":11,"sourceOrder":26},{"id":"chuong-19-28","title":"Chương 19","label":"Chương 19","slug":"chuong-19","status":"public","imported":true,"pageCount":19,"sourceOrder":27},{"id":"chuong-19-5-29","title":"Chương 19.5","label":"Chương 19.5","slug":"chuong-19-5","status":"public","imported":true,"pageCount":17,"sourceOrder":28},{"id":"chuong-20-30","title":"Chương 20","label":"Chương 20","slug":"chuong-20","status":"public","imported":true,"pageCount":22,"sourceOrder":29},{"id":"chuong-20-5-31","title":"Chương 20.5","label":"Chương 20.5","slug":"chuong-20-5","status":"public","imported":true,"pageCount":9,"sourceOrder":30},{"id":"chuong-21-32","title":"Chương 21","label":"Chương 21","slug":"chuong-21","status":"public","imported":true,"pageCount":17,"sourceOrder":31},{"id":"chuong-21-5-33","title":"Chương 21.5","label":"Chương 21.5","slug":"chuong-21-5","status":"public","imported":true,"pageCount":17,"sourceOrder":32},{"id":"chuong-22-34","title":"Chương 22","label":"Chương 22","slug":"chuong-22","status":"public","imported":true,"pageCount":29,"sourceOrder":33},{"id":"chuong-23-35","title":"Chương 23","label":"Chương 23","slug":"chuong-23","status":"public","imported":true,"pageCount":34,"sourceOrder":34},{"id":"chuong-24-36","title":"Chương 24","label":"Chương 24","slug":"chuong-24","status":"public","imported":true,"pageCount":36,"sourceOrder":35},{"id":"chuong-25-37","title":"Chương 25","label":"Chương 25","slug":"chuong-25","status":"public","imported":true,"pageCount":37,"sourceOrder":36},{"id":"chuong-26-38","title":"Chương 26","label":"Chương 26","slug":"chuong-26","status":"public","imported":true,"pageCount":36,"sourceOrder":37},{"id":"chuong-27-39","title":"Chương 27","label":"Chương 27","slug":"chuong-27","status":"public","imported":true,"pageCount":34,"sourceOrder":38},{"id":"chuong-28-40","title":"Chương 28","label":"Chương 28","slug":"chuong-28","status":"public","imported":true,"pageCount":57,"sourceOrder":39},{"id":"chuong-29-41","title":"Chương 29","label":"Chương 29","slug":"chuong-29","status":"public","imported":true,"pageCount":43,"sourceOrder":40},{"id":"chuong-30-42","title":"Chương 30","label":"Chương 30","slug":"chuong-30","status":"public","imported":true,"pageCount":47,"sourceOrder":41},{"id":"chuong-31-43","title":"Chương 31","label":"Chương 31","slug":"chuong-31","status":"public","imported":true,"pageCount":62,"sourceOrder":42},{"id":"chuong-32-44","title":"Chương 32","label":"Chương 32","slug":"chuong-32","status":"public","imported":true,"pageCount":77,"sourceOrder":43},{"id":"chuong-33-45","title":"Chương 33","label":"Chương 33","slug":"chuong-33","status":"public","imported":true,"pageCount":54,"sourceOrder":44},{"id":"chuong-34-46","title":"Chương 34","label":"Chương 34","slug":"chuong-34","status":"public","imported":true,"pageCount":36,"sourceOrder":45},{"id":"chuong-35-47","title":"Chương 35","label":"Chương 35","slug":"chuong-35","status":"public","imported":true,"pageCount":39,"sourceOrder":46},{"id":"chuong-36-48","title":"Chương 36","label":"Chương 36","slug":"chuong-36","status":"public","imported":true,"pageCount":50,"sourceOrder":47},{"id":"chuong-37-49","title":"Chương 37","label":"Chương 37","slug":"chuong-37","status":"public","imported":true,"pageCount":37,"sourceOrder":48},{"id":"chuong-38-50","title":"Chương 38","label":"Chương 38","slug":"chuong-38","status":"public","imported":true,"pageCount":37,"sourceOrder":49},{"id":"chuong-39-51","title":"Chương 39","label":"Chương 39","slug":"chuong-39","status":"public","imported":true,"pageCount":34,"sourceOrder":50},{"id":"chuong-40-52","title":"Chương 40","label":"Chương 40","slug":"chuong-40","status":"public","imported":true,"pageCount":89,"sourceOrder":51},{"id":"chuong-41-53","title":"Chương 41","label":"Chương 41","slug":"chuong-41","status":"public","imported":true,"pageCount":31,"sourceOrder":52},{"id":"chuong-42-54","title":"Chương 42","label":"Chương 42","slug":"chuong-42","status":"public","imported":true,"pageCount":62,"sourceOrder":53},{"id":"chuong-43-55","title":"Chương 43","label":"Chương 43","slug":"chuong-43","status":"public","imported":true,"pageCount":34,"sourceOrder":54},{"id":"chuong-44-56","title":"Chương 44","label":"Chương 44","slug":"chuong-44","status":"public","imported":true,"pageCount":53,"sourceOrder":55},{"id":"chuong-45-57","title":"Chương 45","label":"Chương 45","slug":"chuong-45","status":"public","imported":true,"pageCount":81,"sourceOrder":56},{"id":"chuong-46-58","title":"Chương 46","label":"Chương 46","slug":"chuong-46","status":"public","imported":true,"pageCount":31,"sourceOrder":57},{"id":"chuong-47-59","title":"Chương 47","label":"Chương 47","slug":"chuong-47","status":"public","imported":true,"pageCount":56,"sourceOrder":58},{"id":"chuong-48-60","title":"Chương 48","label":"Chương 48","slug":"chuong-48","status":"public","imported":true,"pageCount":28,"sourceOrder":59},{"id":"chuong-49-61","title":"Chương 49","label":"Chương 49","slug":"chuong-49","status":"public","imported":true,"pageCount":61,"sourceOrder":60},{"id":"chuong-49-5-62","title":"Chương 49.5","label":"Chương 49.5","slug":"chuong-49-5","status":"public","imported":true,"pageCount":4,"sourceOrder":61},{"id":"chuong-50-63","title":"Chương 50","label":"Chương 50","slug":"chuong-50","status":"public","imported":true,"pageCount":55,"sourceOrder":62},{"id":"chuong-51-64","title":"Chương 51","label":"Chương 51","slug":"chuong-51","status":"public","imported":true,"pageCount":35,"sourceOrder":63},{"id":"chuong-52-65","title":"Chương 52","label":"Chương 52","slug":"chuong-52","status":"public","imported":true,"pageCount":51,"sourceOrder":64},{"id":"chuong-53-66","title":"Chương 53","label":"Chương 53","slug":"chuong-53","status":"public","imported":true,"pageCount":37,"sourceOrder":65},{"id":"chuong-54-67","title":"Chương 54","label":"Chương 54","slug":"chuong-54","status":"public","imported":true,"pageCount":57,"sourceOrder":66},{"id":"chuong-55-68","title":"Chương 55","label":"Chương 55","slug":"chuong-55","status":"public","imported":true,"pageCount":38,"sourceOrder":67},{"id":"chuong-56-69","title":"Chương 56","label":"Chương 56","slug":"chuong-56","status":"public","imported":true,"pageCount":32,"sourceOrder":68},{"id":"chuong-57-70","title":"Chương 57","label":"Chương 57","slug":"chuong-57","status":"public","imported":true,"pageCount":34,"sourceOrder":69},{"id":"chuong-58-71","title":"Chương 58","label":"Chương 58","slug":"chuong-58","status":"public","imported":true,"pageCount":29,"sourceOrder":70},{"id":"chuong-59-72","title":"Chương 59","label":"Chương 59","slug":"chuong-59","status":"public","imported":true,"pageCount":52,"sourceOrder":71},{"id":"chuong-60-73","title":"Chương 60","label":"Chương 60","slug":"chuong-60","status":"public","imported":true,"pageCount":48,"sourceOrder":72},{"id":"chuong-61-74","title":"Chương 61","label":"Chương 61","slug":"chuong-61","status":"public","imported":true,"pageCount":47,"sourceOrder":73},{"id":"chuong-62-75","title":"Chương 62","label":"Chương 62","slug":"chuong-62","status":"public","imported":true,"pageCount":50,"sourceOrder":74},{"id":"chuong-63-76","title":"Chương 63","label":"Chương 63","slug":"chuong-63","status":"public","imported":true,"pageCount":32,"sourceOrder":75},{"id":"chuong-64-77","title":"Chương 64","label":"Chương 64","slug":"chuong-64","status":"public","imported":true,"pageCount":41,"sourceOrder":76},{"id":"chuong-65-78","title":"Chương 65","label":"Chương 65","slug":"chuong-65","status":"public","imported":true,"pageCount":34,"sourceOrder":77},{"id":"chuong-66-79","title":"Chương 66","label":"Chương 66","slug":"chuong-66","status":"public","imported":true,"pageCount":58,"sourceOrder":78},{"id":"chuong-67-80","title":"Chương 67","label":"Chương 67","slug":"chuong-67","status":"public","imported":true,"pageCount":38,"sourceOrder":79},{"id":"chuong-68-81","title":"Chương 68","label":"Chương 68","slug":"chuong-68","status":"public","imported":true,"pageCount":40,"sourceOrder":80},{"id":"chuong-69-82","title":"Chương 69","label":"Chương 69","slug":"chuong-69","status":"public","imported":true,"pageCount":35,"sourceOrder":81},{"id":"chuong-70-83","title":"Chương 70","label":"Chương 70","slug":"chuong-70","status":"public","imported":true,"pageCount":35,"sourceOrder":82},{"id":"chuong-71-84","title":"Chương 71","label":"Chương 71","slug":"chuong-71","status":"public","imported":true,"pageCount":35,"sourceOrder":83},{"id":"chuong-72-85","title":"Chương 72","label":"Chương 72","slug":"chuong-72","status":"public","imported":true,"pageCount":44,"sourceOrder":84},{"id":"chuong-73-86","title":"Chương 73","label":"Chương 73","slug":"chuong-73","status":"public","imported":true,"pageCount":40,"sourceOrder":85},{"id":"chuong-74-87","title":"Chương 74","label":"Chương 74","slug":"chuong-74","status":"public","imported":true,"pageCount":48,"sourceOrder":86},{"id":"chuong-75-88","title":"Chương 75","label":"Chương 75","slug":"chuong-75","status":"public","imported":true,"pageCount":46,"sourceOrder":87},{"id":"chuong-76-89","title":"Chương 76","label":"Chương 76","slug":"chuong-76","status":"public","imported":true,"pageCount":36,"sourceOrder":88},{"id":"chuong-77-90","title":"Chương 77","label":"Chương 77","slug":"chuong-77","status":"public","imported":true,"pageCount":45,"sourceOrder":89},{"id":"chuong-78-91","title":"Chương 78","label":"Chương 78","slug":"chuong-78","status":"public","imported":true,"pageCount":35,"sourceOrder":90},{"id":"chuong-79-92","title":"Chương 79","label":"Chương 79","slug":"chuong-79","status":"public","imported":true,"pageCount":53,"sourceOrder":91},{"id":"chuong-80-93","title":"Chương 80","label":"Chương 80","slug":"chuong-80","status":"public","imported":true,"pageCount":43,"sourceOrder":92},{"id":"chuong-81-94","title":"Chương 81","label":"Chương 81","slug":"chuong-81","status":"public","imported":true,"pageCount":44,"sourceOrder":93},{"id":"chuong-82-95","title":"Chương 82","label":"Chương 82","slug":"chuong-82","status":"public","imported":true,"pageCount":43,"sourceOrder":94},{"id":"chuong-83-96","title":"Chương 83","label":"Chương 83","slug":"chuong-83","status":"public","imported":true,"pageCount":43,"sourceOrder":95},{"id":"chuong-84-97","title":"Chương 84","label":"Chương 84","slug":"chuong-84","status":"public","imported":true,"pageCount":38,"sourceOrder":96},{"id":"chuong-85-98","title":"Chương 85","label":"Chương 85","slug":"chuong-85","status":"public","imported":true,"pageCount":40,"sourceOrder":97},{"id":"chuong-86-99","title":"Chương 86","label":"Chương 86","slug":"chuong-86","status":"public","imported":true,"pageCount":40,"sourceOrder":98},{"id":"chuong-87-100","title":"Chương 87","label":"Chương 87","slug":"chuong-87","status":"public","imported":true,"pageCount":40,"sourceOrder":99},{"id":"chuong-88-101","title":"Chương 88","label":"Chương 88","slug":"chuong-88","status":"public","imported":true,"pageCount":44,"sourceOrder":100},{"id":"chuong-89-102","title":"Chương 89","label":"Chương 89","slug":"chuong-89","status":"public","imported":true,"pageCount":46,"sourceOrder":101},{"id":"chuong-90-103","title":"Chương 90","label":"Chương 90","slug":"chuong-90","status":"public","imported":true,"pageCount":43,"sourceOrder":102},{"id":"chuong-91-104","title":"Chương 91","label":"Chương 91","slug":"chuong-91","status":"public","imported":true,"pageCount":41,"sourceOrder":103},{"id":"chuong-92-105","title":"Chương 92","label":"Chương 92","slug":"chuong-92","status":"public","imported":true,"pageCount":50,"sourceOrder":104},{"id":"chuong-93-106","title":"Chương 93","label":"Chương 93","slug":"chuong-93","status":"public","imported":true,"pageCount":41,"sourceOrder":105},{"id":"chuong-94-107","title":"Chương 94","label":"Chương 94","slug":"chuong-94","status":"public","imported":true,"pageCount":39,"sourceOrder":106},{"id":"chuong-95-108","title":"Chương 95","label":"Chương 95","slug":"chuong-95","status":"public","imported":true,"pageCount":44,"sourceOrder":107},{"id":"chuong-96-109","title":"Chương 96","label":"Chương 96","slug":"chuong-96","status":"public","imported":true,"pageCount":50,"sourceOrder":108},{"id":"chuong-97-110","title":"Chương 97","label":"Chương 97","slug":"chuong-97","status":"public","imported":true,"pageCount":44,"sourceOrder":109},{"id":"chuong-98-111","title":"Chương 98","label":"Chương 98","slug":"chuong-98","status":"public","imported":true,"pageCount":31,"sourceOrder":110},{"id":"chuong-99-112","title":"Chương 99","label":"Chương 99","slug":"chuong-99","status":"public","imported":true,"pageCount":34,"sourceOrder":111},{"id":"chuong-100-113","title":"Chương 100","label":"Chương 100","slug":"chuong-100","status":"public","imported":true,"pageCount":46,"sourceOrder":112},{"id":"chuong-101-114","title":"Chương 101","label":"Chương 101","slug":"chuong-101","status":"public","imported":true,"pageCount":43,"sourceOrder":113},{"id":"chuong-102-115","title":"Chương 102","label":"Chương 102","slug":"chuong-102","status":"public","imported":true,"pageCount":39,"sourceOrder":114},{"id":"chuong-103-116","title":"Chương 103","label":"Chương 103","slug":"chuong-103","status":"public","imported":true,"pageCount":51,"sourceOrder":115},{"id":"chuong-104-117","title":"Chương 104","label":"Chương 104","slug":"chuong-104","status":"public","imported":true,"pageCount":44,"sourceOrder":116},{"id":"chuong-105-118","title":"Chương 105","label":"Chương 105","slug":"chuong-105","status":"public","imported":true,"pageCount":55,"sourceOrder":117},{"id":"chuong-106-119","title":"Chương 106","label":"Chương 106","slug":"chuong-106","status":"public","imported":true,"pageCount":37,"sourceOrder":118},{"id":"chuong-107-120","title":"Chương 107","label":"Chương 107","slug":"chuong-107","status":"public","imported":true,"pageCount":52,"sourceOrder":119},{"id":"chuong-108-121","title":"Chương 108","label":"Chương 108","slug":"chuong-108","status":"public","imported":true,"pageCount":34,"sourceOrder":120},{"id":"chuong-109-122","title":"Chương 109","label":"Chương 109","slug":"chuong-109","status":"public","imported":true,"pageCount":44,"sourceOrder":121},{"id":"chuong-110-123","title":"Chương 110","label":"Chương 110","slug":"chuong-110","status":"public","imported":true,"pageCount":52,"sourceOrder":122},{"id":"chuong-111-124","title":"Chương 111","label":"Chương 111","slug":"chuong-111","status":"public","imported":true,"pageCount":48,"sourceOrder":123},{"id":"chuong-112-125","title":"Chương 112","label":"Chương 112","slug":"chuong-112","status":"public","imported":true,"pageCount":58,"sourceOrder":124},{"id":"chuong-113-126","title":"Chương 113","label":"Chương 113","slug":"chuong-113","status":"public","imported":true,"pageCount":46,"sourceOrder":125},{"id":"chuong-114-127","title":"Chương 114","label":"Chương 114","slug":"chuong-114","status":"public","imported":true,"pageCount":50,"sourceOrder":126},{"id":"chuong-115-128","title":"Chương 115","label":"Chương 115","slug":"chuong-115","status":"public","imported":true,"pageCount":42,"sourceOrder":127},{"id":"chuong-116-129","title":"Chương 116","label":"Chương 116","slug":"chuong-116","status":"public","imported":true,"pageCount":44,"sourceOrder":128},{"id":"chuong-117-130","title":"Chương 117","label":"Chương 117","slug":"chuong-117","status":"public","imported":true,"pageCount":43,"sourceOrder":129},{"id":"chuong-118-131","title":"Chương 118","label":"Chương 118","slug":"chuong-118","status":"public","imported":true,"pageCount":184,"sourceOrder":130},{"id":"chuong-119-132","title":"Chương 119","label":"Chương 119","slug":"chuong-119","status":"public","imported":true,"pageCount":46,"sourceOrder":131},{"id":"chuong-120-133","title":"Chương 120","label":"Chương 120","slug":"chuong-120","status":"public","imported":true,"pageCount":44,"sourceOrder":132},{"id":"chuong-121-134","title":"Chương 121","label":"Chương 121","slug":"chuong-121","status":"public","imported":true,"pageCount":44,"sourceOrder":133},{"id":"chuong-122-135","title":"Chương 122","label":"Chương 122","slug":"chuong-122","status":"public","imported":true,"pageCount":44,"sourceOrder":134},{"id":"chuong-123-136","title":"Chương 123","label":"Chương 123","slug":"chuong-123","status":"public","imported":true,"pageCount":131,"sourceOrder":135},{"id":"chuong-124-137","title":"Chương 124","label":"Chương 124","slug":"chuong-124","status":"public","imported":true,"pageCount":38,"sourceOrder":136},{"id":"chuong-125-138","title":"Chương 125","label":"Chương 125","slug":"chuong-125","status":"public","imported":true,"pageCount":43,"sourceOrder":137},{"id":"chuong-126-139","title":"Chương 126","label":"Chương 126","slug":"chuong-126","status":"public","imported":true,"pageCount":35,"sourceOrder":138},{"id":"chuong-127-140","title":"Chương 127","label":"Chương 127","slug":"chuong-127","status":"public","imported":true,"pageCount":47,"sourceOrder":139},{"id":"chuong-128-141","title":"Chương 128","label":"Chương 128","slug":"chuong-128","status":"public","imported":true,"pageCount":46,"sourceOrder":140},{"id":"chuong-129-142","title":"Chương 129","label":"Chương 129","slug":"chuong-129","status":"public","imported":true,"pageCount":32,"sourceOrder":141},{"id":"chuong-130-143","title":"Chương 130","label":"Chương 130","slug":"chuong-130","status":"public","imported":true,"pageCount":49,"sourceOrder":142},{"id":"chuong-131-144","title":"Chương 131","label":"Chương 131","slug":"chuong-131","status":"public","imported":true,"pageCount":47,"sourceOrder":143},{"id":"chuong-132-145","title":"Chương 132","label":"Chương 132","slug":"chuong-132","status":"public","imported":true,"pageCount":35,"sourceOrder":144},{"id":"chuong-133-146","title":"Chương 133","label":"Chương 133","slug":"chuong-133","status":"public","imported":true,"pageCount":50,"sourceOrder":145},{"id":"chuong-134-147","title":"Chương 134","label":"Chương 134","slug":"chuong-134","status":"public","imported":true,"pageCount":46,"sourceOrder":146},{"id":"chuong-135-148","title":"Chương 135","label":"Chương 135","slug":"chuong-135","status":"public","imported":true,"pageCount":71,"sourceOrder":147},{"id":"chuong-136-149","title":"Chương 136","label":"Chương 136","slug":"chuong-136","status":"public","imported":true,"pageCount":34,"sourceOrder":148},{"id":"chuong-137-150","title":"Chương 137","label":"Chương 137","slug":"chuong-137","status":"public","imported":true,"pageCount":42,"sourceOrder":149},{"id":"chuong-138-151","title":"Chương 138","label":"Chương 138","slug":"chuong-138","status":"public","imported":true,"pageCount":37,"sourceOrder":150},{"id":"chuong-139-152","title":"Chương 139","label":"Chương 139","slug":"chuong-139","status":"public","imported":true,"pageCount":72,"sourceOrder":151},{"id":"chuong-140-153","title":"Chương 140","label":"Chương 140","slug":"chuong-140","status":"public","imported":true,"pageCount":43,"sourceOrder":152},{"id":"chuong-141-154","title":"Chương 141","label":"Chương 141","slug":"chuong-141","status":"public","imported":true,"pageCount":37,"sourceOrder":153},{"id":"chuong-142-155","title":"Chương 142","label":"Chương 142","slug":"chuong-142","status":"public","imported":true,"pageCount":62,"sourceOrder":154},{"id":"chuong-143-156","title":"Chương 143","label":"Chương 143","slug":"chuong-143","status":"public","imported":true,"pageCount":44,"sourceOrder":155},{"id":"chuong-144-157","title":"Chương 144","label":"Chương 144","slug":"chuong-144","status":"public","imported":true,"pageCount":37,"sourceOrder":156},{"id":"chuong-145-158","title":"Chương 145","label":"Chương 145","slug":"chuong-145","status":"public","imported":true,"pageCount":44,"sourceOrder":157},{"id":"chuong-146-159","title":"Chương 146","label":"Chương 146","slug":"chuong-146","status":"public","imported":true,"pageCount":52,"sourceOrder":158},{"id":"chuong-147-160","title":"Chương 147","label":"Chương 147","slug":"chuong-147","status":"public","imported":true,"pageCount":45,"sourceOrder":159},{"id":"chuong-148-161","title":"Chương 148","label":"Chương 148","slug":"chuong-148","status":"public","imported":true,"pageCount":41,"sourceOrder":160},{"id":"chuong-149-162","title":"Chương 149","label":"Chương 149","slug":"chuong-149","status":"public","imported":true,"pageCount":8,"sourceOrder":161},{"id":"chuong-149-1-163","title":"Chương 149.1","label":"Chương 149.1","slug":"chuong-149-1","status":"public","imported":true,"pageCount":50,"sourceOrder":162},{"id":"chuong-150-164","title":"Chương 150","label":"Chương 150","slug":"chuong-150","status":"public","imported":true,"pageCount":44,"sourceOrder":163},{"id":"chuong-151-165","title":"Chương 151","label":"Chương 151","slug":"chuong-151","status":"public","imported":true,"pageCount":43,"sourceOrder":164},{"id":"chuong-152-166","title":"Chương 152","label":"Chương 152","slug":"chuong-152","status":"public","imported":true,"pageCount":43,"sourceOrder":165},{"id":"chuong-153-167","title":"Chương 153","label":"Chương 153","slug":"chuong-153","status":"public","imported":true,"pageCount":40,"sourceOrder":166},{"id":"chuong-154-168","title":"Chương 154","label":"Chương 154","slug":"chuong-154","status":"public","imported":true,"pageCount":55,"sourceOrder":167},{"id":"chuong-155-169","title":"Chương 155","label":"Chương 155","slug":"chuong-155","status":"public","imported":true,"pageCount":54,"sourceOrder":168},{"id":"chuong-156-170","title":"Chương 156","label":"Chương 156","slug":"chuong-156","status":"public","imported":true,"pageCount":49,"sourceOrder":169},{"id":"chuong-157-171","title":"Chương 157","label":"Chương 157","slug":"chuong-157","status":"public","imported":true,"pageCount":39,"sourceOrder":170},{"id":"chuong-158-172","title":"Chương 158","label":"Chương 158","slug":"chuong-158","status":"public","imported":true,"pageCount":29,"sourceOrder":171},{"id":"chuong-159-173","title":"Chương 159","label":"Chương 159","slug":"chuong-159","status":"public","imported":true,"pageCount":44,"sourceOrder":172},{"id":"chuong-160-174","title":"Chương 160","label":"Chương 160","slug":"chuong-160","status":"public","imported":true,"pageCount":41,"sourceOrder":173},{"id":"chuong-161-175","title":"Chương 161","label":"Chương 161","slug":"chuong-161","status":"public","imported":true,"pageCount":20,"sourceOrder":174},{"id":"chuong-162-176","title":"Chương 162","label":"Chương 162","slug":"chuong-162","status":"public","imported":true,"pageCount":26,"sourceOrder":175},{"id":"chuong-163-177","title":"Chương 163","label":"Chương 163","slug":"chuong-163","status":"public","imported":true,"pageCount":38,"sourceOrder":176},{"id":"chuong-164-178","title":"Chương 164","label":"Chương 164","slug":"chuong-164","status":"public","imported":true,"pageCount":18,"sourceOrder":177},{"id":"chuong-165-179","title":"Chương 165","label":"Chương 165","slug":"chuong-165","status":"public","imported":true,"pageCount":108,"sourceOrder":178},{"id":"chuong-166-180","title":"Chương 166","label":"Chương 166","slug":"chuong-166","status":"public","imported":true,"pageCount":47,"sourceOrder":179},{"id":"chuong-167-181","title":"Chương 167","label":"Chương 167","slug":"chuong-167","status":"public","imported":true,"pageCount":173,"sourceOrder":180},{"id":"chuong-168-182","title":"Chương 168","label":"Chương 168","slug":"chuong-168","status":"public","imported":true,"pageCount":52,"sourceOrder":181},{"id":"chuong-169-183","title":"Chương 169","label":"Chương 169","slug":"chuong-169","status":"public","imported":true,"pageCount":39,"sourceOrder":182},{"id":"chuong-170-184","title":"Chương 170","label":"Chương 170","slug":"chuong-170","status":"public","imported":true,"pageCount":43,"sourceOrder":183},{"id":"chuong-171-185","title":"Chương 171","label":"Chương 171","slug":"chuong-171","status":"public","imported":true,"pageCount":14,"sourceOrder":184},{"id":"chuong-172-186","title":"Chương 172","label":"Chương 172","slug":"chuong-172","status":"public","imported":true,"pageCount":45,"sourceOrder":185},{"id":"chuong-173-187","title":"Chương 173","label":"Chương 173","slug":"chuong-173","status":"public","imported":true,"pageCount":42,"sourceOrder":186},{"id":"chuong-174-188","title":"Chương 174","label":"Chương 174","slug":"chuong-174","status":"public","imported":true,"pageCount":47,"sourceOrder":187},{"id":"chuong-175-189","title":"Chương 175","label":"Chương 175","slug":"chuong-175","status":"public","imported":true,"pageCount":52,"sourceOrder":188},{"id":"chuong-176-190","title":"Chương 176","label":"Chương 176","slug":"chuong-176","status":"public","imported":true,"pageCount":117,"sourceOrder":189},{"id":"chuong-177-191","title":"Chương 177","label":"Chương 177","slug":"chuong-177","status":"public","imported":true,"pageCount":48,"sourceOrder":190},{"id":"chuong-178-192","title":"Chương 178","label":"Chương 178","slug":"chuong-178","status":"public","imported":true,"pageCount":20,"sourceOrder":191},{"id":"chuong-179-193","title":"Chương 179","label":"Chương 179","slug":"chuong-179","status":"public","imported":true,"pageCount":18,"sourceOrder":192},{"id":"chuong-180-194","title":"Chương 180","label":"Chương 180","slug":"chuong-180","status":"public","imported":true,"pageCount":52,"sourceOrder":193},{"id":"chuong-181-195","title":"Chương 181","label":"Chương 181","slug":"chuong-181","status":"public","imported":true,"pageCount":21,"sourceOrder":194},{"id":"chuong-182-196","title":"Chương 182","label":"Chương 182","slug":"chuong-182","status":"public","imported":true,"pageCount":22,"sourceOrder":195},{"id":"chuong-183-197","title":"Chương 183","label":"Chương 183","slug":"chuong-183","status":"public","imported":true,"pageCount":22,"sourceOrder":196},{"id":"chuong-184-198","title":"Chương 184","label":"Chương 184","slug":"chuong-184","status":"public","imported":true,"pageCount":110,"sourceOrder":197},{"id":"chuong-185-199","title":"Chương 185","label":"Chương 185","slug":"chuong-185","status":"public","imported":true,"pageCount":116,"sourceOrder":198},{"id":"chuong-186-200","title":"Chương 186","label":"Chương 186","slug":"chuong-186","status":"public","imported":true,"pageCount":141,"sourceOrder":199},{"id":"chuong-187-201","title":"Chương 187","label":"Chương 187","slug":"chuong-187","status":"public","imported":true,"pageCount":6,"sourceOrder":200},{"id":"chuong-188-202","title":"Chương 188","label":"Chương 188","slug":"chuong-188","status":"public","imported":true,"pageCount":123,"sourceOrder":201},{"id":"chuong-189-203","title":"Chương 189","label":"Chương 189","slug":"chuong-189","status":"public","imported":true,"pageCount":20,"sourceOrder":202},{"id":"chuong-190-204","title":"Chương 190","label":"Chương 190","slug":"chuong-190","status":"public","imported":true,"pageCount":7,"sourceOrder":203},{"id":"chuong-191-205","title":"Chương 191","label":"Chương 191","slug":"chuong-191","status":"public","imported":true,"pageCount":6,"sourceOrder":204},{"id":"chuong-192-206","title":"Chương 192","label":"Chương 192","slug":"chuong-192","status":"public","imported":true,"pageCount":20,"sourceOrder":205},{"id":"chuong-193-207","title":"Chương 193","label":"Chương 193","slug":"chuong-193","status":"public","imported":true,"pageCount":149,"sourceOrder":206},{"id":"chuong-194-208","title":"Chương 194","label":"Chương 194","slug":"chuong-194","status":"public","imported":true,"pageCount":50,"sourceOrder":207},{"id":"chuong-195-209","title":"Chương 195","label":"Chương 195","slug":"chuong-195","status":"public","imported":true,"pageCount":19,"sourceOrder":208},{"id":"chuong-196-210","title":"Chương 196","label":"Chương 196","slug":"chuong-196","status":"public","imported":true,"pageCount":19,"sourceOrder":209},{"id":"chuong-197-211","title":"Chương 197","label":"Chương 197","slug":"chuong-197","status":"public","imported":true,"pageCount":131,"sourceOrder":210},{"id":"chuong-198-212","title":"Chương 198","label":"Chương 198","slug":"chuong-198","status":"public","imported":true,"pageCount":18,"sourceOrder":211},{"id":"chuong-199-213","title":"Chương 199","label":"Chương 199","slug":"chuong-199","status":"public","imported":true,"pageCount":129,"sourceOrder":212},{"id":"chuong-200-214","title":"Chương 200","label":"Chương 200","slug":"chuong-200","status":"public","imported":true,"pageCount":18,"sourceOrder":213},{"id":"chuong-201-215","title":"Chương 201","label":"Chương 201","slug":"chuong-201","status":"public","imported":true,"pageCount":17,"sourceOrder":214},{"id":"chuong-202-216","title":"Chương 202","label":"Chương 202","slug":"chuong-202","status":"public","imported":true,"pageCount":18,"sourceOrder":215},{"id":"chuong-203-217","title":"Chương 203","label":"Chương 203","slug":"chuong-203","status":"public","imported":true,"pageCount":19,"sourceOrder":216},{"id":"chuong-204-218","title":"Chương 204","label":"Chương 204","slug":"chuong-204","status":"public","imported":true,"pageCount":18,"sourceOrder":217},{"id":"chuong-205-219","title":"Chương 205","label":"Chương 205","slug":"chuong-205","status":"public","imported":true,"pageCount":18,"sourceOrder":218},{"id":"chuong-206-220","title":"Chương 206","label":"Chương 206","slug":"chuong-206","status":"public","imported":true,"pageCount":23,"sourceOrder":219},{"id":"chuong-207-221","title":"Chương 207","label":"Chương 207","slug":"chuong-207","status":"public","imported":true,"pageCount":22,"sourceOrder":220},{"id":"chuong-208-222","title":"Chương 208","label":"Chương 208","slug":"chuong-208","status":"public","imported":true,"pageCount":16,"sourceOrder":221},{"id":"chuong-209-223","title":"Chương 209","label":"Chương 209","slug":"chuong-209","status":"public","imported":true,"pageCount":115,"sourceOrder":222},{"id":"chuong-210-224","title":"Chương 210","label":"Chương 210","slug":"chuong-210","status":"public","imported":true,"pageCount":53,"sourceOrder":223},{"id":"chuong-211-225","title":"Chương 211","label":"Chương 211","slug":"chuong-211","status":"public","imported":true,"pageCount":34,"sourceOrder":224},{"id":"chuong-212-226","title":"Chương 212","label":"Chương 212","slug":"chuong-212","status":"public","imported":true,"pageCount":69,"sourceOrder":225},{"id":"chuong-213-227","title":"Chương 213","label":"Chương 213","slug":"chuong-213","status":"public","imported":true,"pageCount":36,"sourceOrder":226},{"id":"chuong-214-228","title":"Chương 214","label":"Chương 214","slug":"chuong-214","status":"public","imported":true,"pageCount":39,"sourceOrder":227},{"id":"chuong-215-229","title":"Chương 215","label":"Chương 215","slug":"chuong-215","status":"public","imported":true,"pageCount":124,"sourceOrder":228},{"id":"chuong-216-230","title":"Chương 216","label":"Chương 216","slug":"chuong-216","status":"public","imported":true,"pageCount":110,"sourceOrder":229},{"id":"chuong-217-231","title":"Chương 217","label":"Chương 217","slug":"chuong-217","status":"public","imported":true,"pageCount":41,"sourceOrder":230},{"id":"chuong-218-232","title":"Chương 218","label":"Chương 218","slug":"chuong-218","status":"public","imported":true,"pageCount":63,"sourceOrder":231},{"id":"chuong-219-233","title":"Chương 219","label":"Chương 219","slug":"chuong-219","status":"public","imported":true,"pageCount":125,"sourceOrder":232},{"id":"chuong-220-234","title":"Chương 220","label":"Chương 220","slug":"chuong-220","status":"public","imported":true,"pageCount":35,"sourceOrder":233},{"id":"chuong-221-235","title":"Chương 221","label":"Chương 221","slug":"chuong-221","status":"public","imported":true,"pageCount":141,"sourceOrder":234},{"id":"chuong-222-236","title":"Chương 222","label":"Chương 222","slug":"chuong-222","status":"public","imported":true,"pageCount":34,"sourceOrder":235},{"id":"chuong-223-237","title":"Chương 223","label":"Chương 223","slug":"chuong-223","status":"public","imported":true,"pageCount":76,"sourceOrder":236},{"id":"chuong-224-238","title":"Chương 224","label":"Chương 224","slug":"chuong-224","status":"public","imported":true,"pageCount":135,"sourceOrder":237},{"id":"chuong-225-239","title":"Chương 225","label":"Chương 225","slug":"chuong-225","status":"public","imported":true,"pageCount":122,"sourceOrder":238},{"id":"chuong-226-240","title":"Chương 226","label":"Chương 226","slug":"chuong-226","status":"public","imported":true,"pageCount":58,"sourceOrder":239},{"id":"chuong-227-241","title":"Chương 227","label":"Chương 227","slug":"chuong-227","status":"public","imported":true,"pageCount":129,"sourceOrder":240},{"id":"chuong-228-242","title":"Chương 228","label":"Chương 228","slug":"chuong-228","status":"public","imported":true,"pageCount":135,"sourceOrder":241},{"id":"chuong-229-243","title":"Chương 229","label":"Chương 229","slug":"chuong-229","status":"public","imported":true,"pageCount":47,"sourceOrder":242},{"id":"chuong-230-244","title":"Chương 230","label":"Chương 230","slug":"chuong-230","status":"public","imported":true,"pageCount":81,"sourceOrder":243},{"id":"chuong-231-245","title":"Chương 231","label":"Chương 231","slug":"chuong-231","status":"public","imported":true,"pageCount":34,"sourceOrder":244},{"id":"chuong-232-246","title":"Chương 232","label":"Chương 232","slug":"chuong-232","status":"public","imported":true,"pageCount":63,"sourceOrder":245},{"id":"chuong-233-247","title":"Chương 233","label":"Chương 233","slug":"chuong-233","status":"public","imported":true,"pageCount":49,"sourceOrder":246},{"id":"chuong-234-248","title":"Chương 234","label":"Chương 234","slug":"chuong-234","status":"public","imported":true,"pageCount":73,"sourceOrder":247},{"id":"chuong-235-249","title":"Chương 235","label":"Chương 235","slug":"chuong-235","status":"public","imported":true,"pageCount":51,"sourceOrder":248},{"id":"chuong-236-250","title":"Chương 236","label":"Chương 236","slug":"chuong-236","status":"public","imported":true,"pageCount":42,"sourceOrder":249},{"id":"chuong-237-251","title":"Chương 237","label":"Chương 237","slug":"chuong-237","status":"public","imported":true,"pageCount":127,"sourceOrder":250},{"id":"chuong-238-252","title":"Chương 238","label":"Chương 238","slug":"chuong-238","status":"public","imported":true,"pageCount":60,"sourceOrder":251},{"id":"chuong-239-253","title":"Chương 239","label":"Chương 239","slug":"chuong-239","status":"public","imported":true,"pageCount":75,"sourceOrder":252},{"id":"chuong-239-1-254","title":"Chương 239.1","label":"Chương 239.1","slug":"chuong-239-1","status":"public","imported":true,"pageCount":57,"sourceOrder":253},{"id":"chuong-240-255","title":"Chương 240","label":"Chương 240","slug":"chuong-240","status":"public","imported":true,"pageCount":50,"sourceOrder":254},{"id":"chuong-241-256","title":"Chương 241","label":"Chương 241","slug":"chuong-241","status":"public","imported":true,"pageCount":10,"sourceOrder":255},{"id":"chuong-242-257","title":"Chương 242","label":"Chương 242","slug":"chuong-242","status":"public","imported":true,"pageCount":10,"sourceOrder":256},{"id":"chuong-243-258","title":"Chương 243","label":"Chương 243","slug":"chuong-243","status":"public","imported":true,"pageCount":13,"sourceOrder":257},{"id":"chuong-244-259","title":"Chương 244","label":"Chương 244","slug":"chuong-244","status":"public","imported":true,"pageCount":14,"sourceOrder":258},{"id":"chuong-245-260","title":"Chương 245","label":"Chương 245","slug":"chuong-245","status":"public","imported":true,"pageCount":11,"sourceOrder":259},{"id":"chuong-246-261","title":"Chương 246","label":"Chương 246","slug":"chuong-246","status":"public","imported":true,"pageCount":10,"sourceOrder":260},{"id":"chuong-247-262","title":"Chương 247","label":"Chương 247","slug":"chuong-247","status":"public","imported":true,"pageCount":14,"sourceOrder":261},{"id":"chuong-248-263","title":"Chương 248","label":"Chương 248","slug":"chuong-248","status":"public","imported":true,"pageCount":10,"sourceOrder":262},{"id":"chuong-249-264","title":"Chương 249","label":"Chương 249","slug":"chuong-249","status":"public","imported":true,"pageCount":15,"sourceOrder":263},{"id":"chuong-250-265","title":"Chương 250","label":"Chương 250","slug":"chuong-250","status":"public","imported":true,"pageCount":10,"sourceOrder":264},{"id":"chuong-251-266","title":"Chương 251","label":"Chương 251","slug":"chuong-251","status":"public","imported":true,"pageCount":10,"sourceOrder":265},{"id":"chuong-252-267","title":"Chương 252","label":"Chương 252","slug":"chuong-252","status":"public","imported":true,"pageCount":16,"sourceOrder":266},{"id":"chuong-253-268","title":"Chương 253","label":"Chương 253","slug":"chuong-253","status":"public","imported":true,"pageCount":10,"sourceOrder":267},{"id":"chuong-254-269","title":"Chương 254","label":"Chương 254","slug":"chuong-254","status":"public","imported":true,"pageCount":10,"sourceOrder":268},{"id":"chuong-255-270","title":"Chương 255","label":"Chương 255","slug":"chuong-255","status":"public","imported":true,"pageCount":10,"sourceOrder":269},{"id":"chuong-256-271","title":"Chương 256","label":"Chương 256","slug":"chuong-256","status":"public","imported":true,"pageCount":18,"sourceOrder":270},{"id":"chuong-257-272","title":"Chương 257","label":"Chương 257","slug":"chuong-257","status":"public","imported":true,"pageCount":10,"sourceOrder":271},{"id":"chuong-258-273","title":"Chương 258","label":"Chương 258","slug":"chuong-258","status":"public","imported":true,"pageCount":9,"sourceOrder":272},{"id":"chuong-259-274","title":"Chương 259","label":"Chương 259","slug":"chuong-259","status":"public","imported":true,"pageCount":10,"sourceOrder":273},{"id":"chuong-260-275","title":"Chương 260","label":"Chương 260","slug":"chuong-260","status":"public","imported":true,"pageCount":10,"sourceOrder":274},{"id":"chuong-261-276","title":"Chương 261","label":"Chương 261","slug":"chuong-261","status":"public","imported":true,"pageCount":103,"sourceOrder":275},{"id":"chuong-262-277","title":"Chương 262","label":"Chương 262","slug":"chuong-262","status":"public","imported":true,"pageCount":11,"sourceOrder":276},{"id":"chuong-263-278","title":"Chương 263","label":"Chương 263","slug":"chuong-263","status":"public","imported":true,"pageCount":8,"sourceOrder":277},{"id":"chuong-265-280","title":"Chương 265","label":"Chương 265","slug":"chuong-265","status":"public","imported":true,"pageCount":6,"sourceOrder":279},{"id":"chuong-266-281","title":"Chương 266","label":"Chương 266","slug":"chuong-266","status":"public","imported":true,"pageCount":11,"sourceOrder":280},{"id":"chuong-267-282","title":"Chương 267","label":"Chương 267","slug":"chuong-267","status":"public","imported":true,"pageCount":4,"sourceOrder":281},{"id":"chuong-268-283","title":"Chương 268","label":"Chương 268","slug":"chuong-268","status":"public","imported":true,"pageCount":5,"sourceOrder":282},{"id":"chuong-269-284","title":"Chương 269","label":"Chương 269","slug":"chuong-269","status":"public","imported":true,"pageCount":7,"sourceOrder":283},{"id":"chuong-270-285","title":"Chương 270","label":"Chương 270","slug":"chuong-270","status":"public","imported":true,"pageCount":7,"sourceOrder":284},{"id":"chuong-271-286","title":"Chương 271","label":"Chương 271","slug":"chuong-271","status":"public","imported":true,"pageCount":7,"sourceOrder":285},{"id":"chuong-272-287","title":"Chương 272","label":"Chương 272","slug":"chuong-272","status":"public","imported":true,"pageCount":8,"sourceOrder":286},{"id":"chuong-273-288","title":"Chương 273","label":"Chương 273","slug":"chuong-273","status":"public","imported":true,"pageCount":7,"sourceOrder":287},{"id":"chuong-274-289","title":"Chương 274","label":"Chương 274","slug":"chuong-274","status":"public","imported":true,"pageCount":11,"sourceOrder":288},{"id":"chuong-275-290","title":"Chương 275","label":"Chương 275","slug":"chuong-275","status":"public","imported":true,"pageCount":6,"sourceOrder":289},{"id":"chuong-276-291","title":"Chương 276","label":"Chương 276","slug":"chuong-276","status":"public","imported":true,"pageCount":5,"sourceOrder":290},{"id":"chuong-277-292","title":"Chương 277","label":"Chương 277","slug":"chuong-277","status":"public","imported":true,"pageCount":7,"sourceOrder":291},{"id":"chuong-278-293","title":"Chương 278","label":"Chương 278","slug":"chuong-278","status":"public","imported":true,"pageCount":6,"sourceOrder":292},{"id":"chuong-279-294","title":"Chương 279","label":"Chương 279","slug":"chuong-279","status":"public","imported":true,"pageCount":8,"sourceOrder":293},{"id":"chuong-280-295","title":"Chương 280","label":"Chương 280","slug":"chuong-280","status":"public","imported":true,"pageCount":7,"sourceOrder":294},{"id":"chuong-281-296","title":"Chương 281","label":"Chương 281","slug":"chuong-281","status":"public","imported":true,"pageCount":7,"sourceOrder":295},{"id":"chuong-282-297","title":"Chương 282","label":"Chương 282","slug":"chuong-282","status":"public","imported":true,"pageCount":5,"sourceOrder":296},{"id":"chuong-283-298","title":"Chương 283","label":"Chương 283","slug":"chuong-283","status":"public","imported":true,"pageCount":7,"sourceOrder":297},{"id":"chuong-284-299","title":"Chương 284","label":"Chương 284","slug":"chuong-284","status":"public","imported":true,"pageCount":7,"sourceOrder":298},{"id":"chuong-285-300","title":"Chương 285","label":"Chương 285","slug":"chuong-285","status":"public","imported":true,"pageCount":5,"sourceOrder":299},{"id":"chuong-286-301","title":"Chương 286","label":"Chương 286","slug":"chuong-286","status":"public","imported":true,"pageCount":7,"sourceOrder":300},{"id":"chuong-287-302","title":"Chương 287","label":"Chương 287","slug":"chuong-287","status":"public","imported":true,"pageCount":6,"sourceOrder":301},{"id":"chuong-288-303","title":"Chương 288","label":"Chương 288","slug":"chuong-288","status":"public","imported":true,"pageCount":6,"sourceOrder":302},{"id":"chuong-289-304","title":"Chương 289","label":"Chương 289","slug":"chuong-289","status":"public","imported":true,"pageCount":6,"sourceOrder":303},{"id":"chuong-290-305","title":"Chương 290","label":"Chương 290","slug":"chuong-290","status":"public","imported":true,"pageCount":7,"sourceOrder":304},{"id":"chuong-291-306","title":"Chương 291","label":"Chương 291","slug":"chuong-291","status":"public","imported":true,"pageCount":6,"sourceOrder":305},{"id":"chuong-292-307","title":"Chương 292","label":"Chương 292","slug":"chuong-292","status":"public","imported":true,"pageCount":7,"sourceOrder":306},{"id":"chuong-293-308","title":"Chương 293","label":"Chương 293","slug":"chuong-293","status":"public","imported":true,"pageCount":7,"sourceOrder":307},{"id":"chuong-294-309","title":"Chương 294","label":"Chương 294","slug":"chuong-294","status":"public","imported":true,"pageCount":7,"sourceOrder":308},{"id":"chuong-295-310","title":"Chương 295","label":"Chương 295","slug":"chuong-295","status":"public","imported":true,"pageCount":7,"sourceOrder":309},{"id":"chuong-296-311","title":"Chương 296","label":"Chương 296","slug":"chuong-296","status":"public","imported":true,"pageCount":7,"sourceOrder":310},{"id":"chuong-297-312","title":"Chương 297","label":"Chương 297","slug":"chuong-297","status":"public","imported":true,"pageCount":7,"sourceOrder":311},{"id":"chuong-298-313","title":"Chương 298","label":"Chương 298","slug":"chuong-298","status":"public","imported":true,"pageCount":7,"sourceOrder":312},{"id":"chuong-299-314","title":"Chương 299","label":"Chương 299","slug":"chuong-299","status":"public","imported":true,"pageCount":6,"sourceOrder":313},{"id":"chuong-300-315","title":"Chương 300","label":"Chương 300","slug":"chuong-300","status":"public","imported":true,"pageCount":7,"sourceOrder":314},{"id":"chuong-301-316","title":"Chương 301","label":"Chương 301","slug":"chuong-301","status":"public","imported":true,"pageCount":7,"sourceOrder":315},{"id":"chuong-302-317","title":"Chương 302","label":"Chương 302","slug":"chuong-302","status":"public","imported":true,"pageCount":7,"sourceOrder":316},{"id":"chuong-303-318","title":"Chương 303","label":"Chương 303","slug":"chuong-303","status":"public","imported":true,"pageCount":8,"sourceOrder":317},{"id":"chuong-304-319","title":"Chương 304","label":"Chương 304","slug":"chuong-304","status":"public","imported":true,"pageCount":8,"sourceOrder":318},{"id":"chuong-305-320","title":"Chương 305","label":"Chương 305","slug":"chuong-305","status":"public","imported":true,"pageCount":7,"sourceOrder":319},{"id":"chuong-306-321","title":"Chương 306","label":"Chương 306","slug":"chuong-306","status":"public","imported":true,"pageCount":7,"sourceOrder":320},{"id":"chuong-307-322","title":"Chương 307","label":"Chương 307","slug":"chuong-307","status":"public","imported":true,"pageCount":7,"sourceOrder":321},{"id":"chuong-308-323","title":"Chương 308","label":"Chương 308","slug":"chuong-308","status":"public","imported":true,"pageCount":8,"sourceOrder":322},{"id":"chuong-309-324","title":"Chương 309","label":"Chương 309","slug":"chuong-309","status":"public","imported":true,"pageCount":8,"sourceOrder":323},{"id":"chuong-310-325","title":"Chương 310","label":"Chương 310","slug":"chuong-310","status":"public","imported":true,"pageCount":8,"sourceOrder":324},{"id":"chuong-311-326","title":"Chương 311","label":"Chương 311","slug":"chuong-311","status":"public","imported":true,"pageCount":9,"sourceOrder":325},{"id":"chuong-312-327","title":"Chương 312","label":"Chương 312","slug":"chuong-312","status":"public","imported":true,"pageCount":7,"sourceOrder":326},{"id":"chuong-313-328","title":"Chương 313","label":"Chương 313","slug":"chuong-313","status":"public","imported":true,"pageCount":7,"sourceOrder":327},{"id":"chuong-314-329","title":"Chương 314","label":"Chương 314","slug":"chuong-314","status":"public","imported":true,"pageCount":8,"sourceOrder":328},{"id":"chuong-316-330","title":"Chương 316","label":"Chương 316","slug":"chuong-316","status":"public","imported":true,"pageCount":7,"sourceOrder":329},{"id":"chuong-317-331","title":"Chương 317","label":"Chương 317","slug":"chuong-317","status":"public","imported":true,"pageCount":6,"sourceOrder":330},{"id":"chuong-318-332","title":"Chương 318","label":"Chương 318","slug":"chuong-318","status":"public","imported":true,"pageCount":7,"sourceOrder":331},{"id":"chuong-319-333","title":"Chương 319","label":"Chương 319","slug":"chuong-319","status":"public","imported":true,"pageCount":6,"sourceOrder":332},{"id":"chuong-320-334","title":"Chương 320","label":"Chương 320","slug":"chuong-320","status":"public","imported":true,"pageCount":7,"sourceOrder":333},{"id":"chuong-321-335","title":"Chương 321","label":"Chương 321","slug":"chuong-321","status":"public","imported":true,"pageCount":7,"sourceOrder":334},{"id":"chuong-322-336","title":"Chương 322","label":"Chương 322","slug":"chuong-322","status":"public","imported":true,"pageCount":6,"sourceOrder":335},{"id":"chuong-323-337","title":"Chương 323","label":"Chương 323","slug":"chuong-323","status":"public","imported":true,"pageCount":7,"sourceOrder":336},{"id":"chuong-324-338","title":"Chương 324","label":"Chương 324","slug":"chuong-324","status":"public","imported":true,"pageCount":6,"sourceOrder":337},{"id":"chuong-325-339","title":"Chương 325","label":"Chương 325","slug":"chuong-325","status":"public","imported":true,"pageCount":5,"sourceOrder":338}]},"chapter":{"id":"chuong-192-206","title":"Chương 192","label":"Chương 192","slug":"chuong-192","status":"public","imported":true,"pageCount":20,"sourceOrder":205,"pages":[{"index":0,"sourceUrl":"https://s135.hinhhinh.com/13646/192/0.jpg?gt=hdfgdfg","src":"https://s3.vn-hcm-1.vietnix.cloud/cuontruyen/imports/cao-vo-ha-canh-en-mot-van-nam-sau-893sqz/chuong-192-206/001.webp","storageKey":"https://s3.vn-hcm-1.vietnix.cloud/cuontruyen/imports/cao-vo-ha-canh-en-mot-van-nam-sau-893sqz/chuong-192-206/001.webp","width":900,"height":1061,"originalBytes":356912,"storedBytes":173562,"optimized":true,"order":0,"imageUrl":"https://s3.vn-hcm-1.vietnix.cloud/cuontruyen/imports/cao-vo-ha-canh-en-mot-van-nam-sau-893sqz/chuong-192-206/001.webp"},{"index":1,"sourceUrl":"https://s135.hinhhinh.com/13646/192/1.jpg?gt=hdfgdfg","src":"https://s3.vn-hcm-1.vietnix.cloud/cuontruyen/imports/cao-vo-ha-canh-en-mot-van-nam-sau-893sqz/chuong-192-206/002.jpg","storageKey":"https://s3.vn-hcm-1.vietnix.cloud/cuontruyen/imports/cao-vo-ha-canh-en-mot-van-nam-sau-893sqz/chuong-192-206/002.jpg","width":null,"height":null,"originalBytes":74309,"storedBytes":74309,"optimized":false,"order":1,"imageUrl":"https://s3.vn-hcm-1.vietnix.cloud/cuontruyen/imports/cao-vo-ha-canh-en-mot-van-nam-sau-893sqz/chuong-192-206/002.jpg"},{"index":2,"sourceUrl":"https://s135.hinhhinh.com/13646/192/2.jpg?gt=hdfgdfg","src":"https://s3.vn-hcm-1.vietnix.cloud/cuontruyen/imports/cao-vo-ha-canh-en-mot-van-nam-sau-893sqz/chuong-192-206/003.jpg","storageKey":"https://s3.vn-hcm-1.vietnix.cloud/cuontruyen/imports/cao-vo-ha-canh-en-mot-van-nam-sau-893sqz/chuong-192-206/003.jpg","width":null,"height":null,"originalBytes":59482,"storedBytes":59482,"optimized":false,"order":2,"imageUrl":"https://s3.vn-hcm-1.vietnix.cloud/cuontruyen/imports/cao-vo-ha-canh-en-mot-van-nam-sau-893sqz/chuong-192-206/003.jpg"},{"index":3,"sourceUrl":"https://s135.hinhhinh.com/13646/192/3.jpg?gt=hdfgdfg","src":"https://s3.vn-hcm-1.vietnix.cloud/cuontruyen/imports/cao-vo-ha-canh-en-mot-van-nam-sau-893sqz/chuong-192-206/004.webp","storageKey":"https://s3.vn-hcm-1.vietnix.cloud/cuontruyen/imports/cao-vo-ha-canh-en-mot-van-nam-sau-893sqz/chuong-192-206/004.webp","width":720,"height":5869,"originalBytes":637652,"storedBytes":481794,"optimized":true,"order":3,"imageUrl":"https://s3.vn-hcm-1.vietnix.cloud/cuontruyen/imports/cao-vo-ha-canh-en-mot-van-nam-sau-893sqz/chuong-192-206/004.webp"},{"index":4,"sourceUrl":"https://s135.hinhhinh.com/13646/192/4.jpg?gt=hdfgdfg","src":"https://s3.vn-hcm-1.vietnix.cloud/cuontruyen/imports/cao-vo-ha-canh-en-mot-van-nam-sau-893sqz/chuong-192-206/005.webp","storageKey":"https://s3.vn-hcm-1.vietnix.cloud/cuontruyen/imports/cao-vo-ha-canh-en-mot-van-nam-sau-893sqz/chuong-192-206/005.webp","width":720,"height":6774,"originalBytes":741705,"storedBytes":566692,"optimized":true,"order":4,"imageUrl":"https://s3.vn-hcm-1.vietnix.cloud/cuontruyen/imports/cao-vo-ha-canh-en-mot-van-nam-sau-893sqz/chuong-192-206/005.webp"},{"index":5,"sourceUrl":"https://s135.hinhhinh.com/13646/192/5.jpg?gt=hdfgdfg","src":"https://s3.vn-hcm-1.vietnix.cloud/cuontruyen/imports/cao-vo-ha-canh-en-mot-van-nam-sau-893sqz/chuong-192-206/006.webp","storageKey":"https://s3.vn-hcm-1.vietnix.cloud/cuontruyen/imports/cao-vo-ha-canh-en-mot-van-nam-sau-893sqz/chuong-192-206/006.webp","width":720,"height":6774,"originalBytes":638259,"storedBytes":455180,"optimized":true,"order":5,"imageUrl":"https://s3.vn-hcm-1.vietnix.cloud/cuontruyen/imports/cao-vo-ha-canh-en-mot-van-nam-sau-893sqz/chuong-192-206/006.webp"},{"index":6,"sourceUrl":"https://s135.hinhhinh.com/13646/192/6.jpg?gt=hdfgdfg","src":"https://s3.vn-hcm-1.vietnix.cloud/cuontruyen/imports/cao-vo-ha-canh-en-mot-van-nam-sau-893sqz/chuong-192-206/007.webp","storageKey":"https://s3.vn-hcm-1.vietnix.cloud/cuontruyen/imports/cao-vo-ha-canh-en-mot-van-nam-sau-893sqz/chuong-192-206/007.webp","width":720,"height":6774,"originalBytes":694130,"storedBytes":501946,"optimized":true,"order":6,"imageUrl":"https://s3.vn-hcm-1.vietnix.cloud/cuontruyen/imports/cao-vo-ha-canh-en-mot-van-nam-sau-893sqz/chuong-192-206/007.webp"},{"index":7,"sourceUrl":"https://s135.hinhhinh.com/13646/192/7.jpg?gt=hdfgdfg","src":"https://s3.vn-hcm-1.vietnix.cloud/cuontruyen/imports/cao-vo-ha-canh-en-mot-van-nam-sau-893sqz/chuong-192-206/008.webp","storageKey":"https://s3.vn-hcm-1.vietnix.cloud/cuontruyen/imports/cao-vo-ha-canh-en-mot-van-nam-sau-893sqz/chuong-192-206/008.webp","width":720,"height":6774,"originalBytes":630292,"storedBytes":456230,"optimized":true,"order":7,"imageUrl":"https://s3.vn-hcm-1.vietnix.cloud/cuontruyen/imports/cao-vo-ha-canh-en-mot-van-nam-sau-893sqz/chuong-192-206/008.webp"},{"index":8,"sourceUrl":"https://s135.hinhhinh.com/13646/192/8.jpg?gt=hdfgdfg","src":"https://s3.vn-hcm-1.vietnix.cloud/cuontruyen/imports/cao-vo-ha-canh-en-mot-van-nam-sau-893sqz/chuong-192-206/009.webp","storageKey":"https://s3.vn-hcm-1.vietnix.cloud/cuontruyen/imports/cao-vo-ha-canh-en-mot-van-nam-sau-893sqz/chuong-192-206/009.webp","width":720,"height":6774,"originalBytes":599899,"storedBytes":425706,"optimized":true,"order":8,"imageUrl":"https://s3.vn-hcm-1.vietnix.cloud/cuontruyen/imports/cao-vo-ha-canh-en-mot-van-nam-sau-893sqz/chuong-192-206/009.webp"},{"index":9,"sourceUrl":"https://s135.hinhhinh.com/13646/192/9.jpg?gt=hdfgdfg","src":"https://s3.vn-hcm-1.vietnix.cloud/cuontruyen/imports/cao-vo-ha-canh-en-mot-van-nam-sau-893sqz/chuong-192-206/010.webp","storageKey":"https://s3.vn-hcm-1.vietnix.cloud/cuontruyen/imports/cao-vo-ha-canh-en-mot-van-nam-sau-893sqz/chuong-192-206/010.webp","width":720,"height":6774,"originalBytes":610250,"storedBytes":442892,"optimized":true,"order":9,"imageUrl":"https://s3.vn-hcm-1.vietnix.cloud/cuontruyen/imports/cao-vo-ha-canh-en-mot-van-nam-sau-893sqz/chuong-192-206/010.webp"},{"index":10,"sourceUrl":"https://s135.hinhhinh.com/13646/192/10.jpg?gt=hdfgdfg","src":"https://s3.vn-hcm-1.vietnix.cloud/cuontruyen/imports/cao-vo-ha-canh-en-mot-van-nam-sau-893sqz/chuong-192-206/011.webp","storageKey":"https://s3.vn-hcm-1.vietnix.cloud/cuontruyen/imports/cao-vo-ha-canh-en-mot-van-nam-sau-893sqz/chuong-192-206/011.webp","width":720,"height":6774,"originalBytes":609398,"storedBytes":447918,"optimized":true,"order":10,"imageUrl":"https://s3.vn-hcm-1.vietnix.cloud/cuontruyen/imports/cao-vo-ha-canh-en-mot-van-nam-sau-893sqz/chuong-192-206/011.webp"},{"index":11,"sourceUrl":"https://s135.hinhhinh.com/13646/192/11.jpg?gt=hdfgdfg","src":"https://s3.vn-hcm-1.vietnix.cloud/cuontruyen/imports/cao-vo-ha-canh-en-mot-van-nam-sau-893sqz/chuong-192-206/012.webp","storageKey":"https://s3.vn-hcm-1.vietnix.cloud/cuontruyen/imports/cao-vo-ha-canh-en-mot-van-nam-sau-893sqz/chuong-192-206/012.webp","width":720,"height":6774,"originalBytes":565238,"storedBytes":409166,"optimized":true,"order":11,"imageUrl":"https://s3.vn-hcm-1.vietnix.cloud/cuontruyen/imports/cao-vo-ha-canh-en-mot-van-nam-sau-893sqz/chuong-192-206/012.webp"},{"index":12,"sourceUrl":"https://s135.hinhhinh.com/13646/192/12.jpg?gt=hdfgdfg","src":"https://s3.vn-hcm-1.vietnix.cloud/cuontruyen/imports/cao-vo-ha-canh-en-mot-van-nam-sau-893sqz/chuong-192-206/013.webp","storageKey":"https://s3.vn-hcm-1.vietnix.cloud/cuontruyen/imports/cao-vo-ha-canh-en-mot-van-nam-sau-893sqz/chuong-192-206/013.webp","width":720,"height":6774,"originalBytes":509063,"storedBytes":346604,"optimized":true,"order":12,"imageUrl":"https://s3.vn-hcm-1.vietnix.cloud/cuontruyen/imports/cao-vo-ha-canh-en-mot-van-nam-sau-893sqz/chuong-192-206/013.webp"},{"index":13,"sourceUrl":"https://s135.hinhhinh.com/13646/192/13.jpg?gt=hdfgdfg","src":"https://s3.vn-hcm-1.vietnix.cloud/cuontruyen/imports/cao-vo-ha-canh-en-mot-van-nam-sau-893sqz/chuong-192-206/014.webp","storageKey":"https://s3.vn-hcm-1.vietnix.cloud/cuontruyen/imports/cao-vo-ha-canh-en-mot-van-nam-sau-893sqz/chuong-192-206/014.webp","width":720,"height":6774,"originalBytes":605099,"storedBytes":449278,"optimized":true,"order":13,"imageUrl":"https://s3.vn-hcm-1.vietnix.cloud/cuontruyen/imports/cao-vo-ha-canh-en-mot-van-nam-sau-893sqz/chuong-192-206/014.webp"},{"index":14,"sourceUrl":"https://s135.hinhhinh.com/13646/192/14.jpg?gt=hdfgdfg","src":"https://s3.vn-hcm-1.vietnix.cloud/cuontruyen/imports/cao-vo-ha-canh-en-mot-van-nam-sau-893sqz/chuong-192-206/015.webp","storageKey":"https://s3.vn-hcm-1.vietnix.cloud/cuontruyen/imports/cao-vo-ha-canh-en-mot-van-nam-sau-893sqz/chuong-192-206/015.webp","width":720,"height":6774,"originalBytes":610507,"storedBytes":443422,"optimized":true,"order":14,"imageUrl":"https://s3.vn-hcm-1.vietnix.cloud/cuontruyen/imports/cao-vo-ha-canh-en-mot-van-nam-sau-893sqz/chuong-192-206/015.webp"},{"index":15,"sourceUrl":"https://s135.hinhhinh.com/13646/192/15.jpg?gt=hdfgdfg","src":"https://s3.vn-hcm-1.vietnix.cloud/cuontruyen/imports/cao-vo-ha-canh-en-mot-van-nam-sau-893sqz/chuong-192-206/016.webp","storageKey":"https://s3.vn-hcm-1.vietnix.cloud/cuontruyen/imports/cao-vo-ha-canh-en-mot-van-nam-sau-893sqz/chuong-192-206/016.webp","width":720,"height":6774,"originalBytes":512376,"storedBytes":351330,"optimized":true,"order":15,"imageUrl":"https://s3.vn-hcm-1.vietnix.cloud/cuontruyen/imports/cao-vo-ha-canh-en-mot-van-nam-sau-893sqz/chuong-192-206/016.webp"},{"index":16,"sourceUrl":"https://s135.hinhhinh.com/13646/192/16.jpg?gt=hdfgdfg","src":"https://s3.vn-hcm-1.vietnix.cloud/cuontruyen/imports/cao-vo-ha-canh-en-mot-van-nam-sau-893sqz/chuong-192-206/017.webp","storageKey":"https://s3.vn-hcm-1.vietnix.cloud/cuontruyen/imports/cao-vo-ha-canh-en-mot-van-nam-sau-893sqz/chuong-192-206/017.webp","width":720,"height":6774,"originalBytes":564440,"storedBytes":393484,"optimized":true,"order":16,"imageUrl":"https://s3.vn-hcm-1.vietnix.cloud/cuontruyen/imports/cao-vo-ha-canh-en-mot-van-nam-sau-893sqz/chuong-192-206/017.webp"},{"index":17,"sourceUrl":"https://s135.hinhhinh.com/13646/192/17.jpg?gt=hdfgdfg","src":"https://s3.vn-hcm-1.vietnix.cloud/cuontruyen/imports/cao-vo-ha-canh-en-mot-van-nam-sau-893sqz/chuong-192-206/018.webp","storageKey":"https://s3.vn-hcm-1.vietnix.cloud/cuontruyen/imports/cao-vo-ha-canh-en-mot-van-nam-sau-893sqz/chuong-192-206/018.webp","width":720,"height":3352,"originalBytes":219110,"storedBytes":148198,"optimized":true,"order":17,"imageUrl":"https://s3.vn-hcm-1.vietnix.cloud/cuontruyen/imports/cao-vo-ha-canh-en-mot-van-nam-sau-893sqz/chuong-192-206/018.webp"},{"index":18,"sourceUrl":"https://s135.hinhhinh.com/13646/192/18.jpg?gt=hdfgdfg","src":"https://s3.vn-hcm-1.vietnix.cloud/cuontruyen/imports/cao-vo-ha-canh-en-mot-van-nam-sau-893sqz/chuong-192-206/019.jpg","storageKey":"https://s3.vn-hcm-1.vietnix.cloud/cuontruyen/imports/cao-vo-ha-canh-en-mot-van-nam-sau-893sqz/chuong-192-206/019.jpg","width":null,"height":null,"originalBytes":74309,"storedBytes":74309,"optimized":false,"order":18,"imageUrl":"https://s3.vn-hcm-1.vietnix.cloud/cuontruyen/imports/cao-vo-ha-canh-en-mot-van-nam-sau-893sqz/chuong-192-206/019.jpg"},{"index":19,"sourceUrl":"https://s135.hinhhinh.com/13646/192/19.jpg?gt=hdfgdfg","src":"https://s3.vn-hcm-1.vietnix.cloud/cuontruyen/imports/cao-vo-ha-canh-en-mot-van-nam-sau-893sqz/chuong-192-206/020.webp","storageKey":"https://s3.vn-hcm-1.vietnix.cloud/cuontruyen/imports/cao-vo-ha-canh-en-mot-van-nam-sau-893sqz/chuong-192-206/020.webp","width":900,"height":1061,"originalBytes":349232,"storedBytes":166106,"optimized":true,"order":19,"imageUrl":"https://s3.vn-hcm-1.vietnix.cloud/cuontruyen/imports/cao-vo-ha-canh-en-mot-van-nam-sau-893sqz/chuong-192-206/020.webp"}]},"chapters":[{"id":"chuong-192-206","title":"Chương 192","label":"Chương 192","slug":"chuong-192","status":"public","imported":true,"pageCount":20,"sourceOrder":205,"pages":[{"index":0,"sourceUrl":"https://s135.hinhhinh.com/13646/192/0.jpg?gt=hdfgdfg","src":"https://s3.vn-hcm-1.vietnix.cloud/cuontruyen/imports/cao-vo-ha-canh-en-mot-van-nam-sau-893sqz/chuong-192-206/001.webp","storageKey":"https://s3.vn-hcm-1.vietnix.cloud/cuontruyen/imports/cao-vo-ha-canh-en-mot-van-nam-sau-893sqz/chuong-192-206/001.webp","width":900,"height":1061,"originalBytes":356912,"storedBytes":173562,"optimized":true,"order":0,"imageUrl":"https://s3.vn-hcm-1.vietnix.cloud/cuontruyen/imports/cao-vo-ha-canh-en-mot-van-nam-sau-893sqz/chuong-192-206/001.webp"},{"index":1,"sourceUrl":"https://s135.hinhhinh.com/13646/192/1.jpg?gt=hdfgdfg","src":"https://s3.vn-hcm-1.vietnix.cloud/cuontruyen/imports/cao-vo-ha-canh-en-mot-van-nam-sau-893sqz/chuong-192-206/002.jpg","storageKey":"https://s3.vn-hcm-1.vietnix.cloud/cuontruyen/imports/cao-vo-ha-canh-en-mot-van-nam-sau-893sqz/chuong-192-206/002.jpg","width":null,"height":null,"originalBytes":74309,"storedBytes":74309,"optimized":false,"order":1,"imageUrl":"https://s3.vn-hcm-1.vietnix.cloud/cuontruyen/imports/cao-vo-ha-canh-en-mot-van-nam-sau-893sqz/chuong-192-206/002.jpg"},{"index":2,"sourceUrl":"https://s135.hinhhinh.com/13646/192/2.jpg?gt=hdfgdfg","src":"https://s3.vn-hcm-1.vietnix.cloud/cuontruyen/imports/cao-vo-ha-canh-en-mot-van-nam-sau-893sqz/chuong-192-206/003.jpg","storageKey":"https://s3.vn-hcm-1.vietnix.cloud/cuontruyen/imports/cao-vo-ha-canh-en-mot-van-nam-sau-893sqz/chuong-192-206/003.jpg","width":null,"height":null,"originalBytes":59482,"storedBytes":59482,"optimized":false,"order":2,"imageUrl":"https://s3.vn-hcm-1.vietnix.cloud/cuontruyen/imports/cao-vo-ha-canh-en-mot-van-nam-sau-893sqz/chuong-192-206/003.jpg"},{"index":3,"sourceUrl":"https://s135.hinhhinh.com/13646/192/3.jpg?gt=hdfgdfg","src":"https://s3.vn-hcm-1.vietnix.cloud/cuontruyen/imports/cao-vo-ha-canh-en-mot-van-nam-sau-893sqz/chuong-192-206/004.webp","storageKey":"https://s3.vn-hcm-1.vietnix.cloud/cuontruyen/imports/cao-vo-ha-canh-en-mot-van-nam-sau-893sqz/chuong-192-206/004.webp","width":720,"height":5869,"originalBytes":637652,"storedBytes":481794,"optimized":true,"order":3,"imageUrl":"https://s3.vn-hcm-1.vietnix.cloud/cuontruyen/imports/cao-vo-ha-canh-en-mot-van-nam-sau-893sqz/chuong-192-206/004.webp"},{"index":4,"sourceUrl":"https://s135.hinhhinh.com/13646/192/4.jpg?gt=hdfgdfg","src":"https://s3.vn-hcm-1.vietnix.cloud/cuontruyen/imports/cao-vo-ha-canh-en-mot-van-nam-sau-893sqz/chuong-192-206/005.webp","storageKey":"https://s3.vn-hcm-1.vietnix.cloud/cuontruyen/imports/cao-vo-ha-canh-en-mot-van-nam-sau-893sqz/chuong-192-206/005.webp","width":720,"height":6774,"originalBytes":741705,"storedBytes":566692,"optimized":true,"order":4,"imageUrl":"https://s3.vn-hcm-1.vietnix.cloud/cuontruyen/imports/cao-vo-ha-canh-en-mot-van-nam-sau-893sqz/chuong-192-206/005.webp"},{"index":5,"sourceUrl":"https://s135.hinhhinh.com/13646/192/5.jpg?gt=hdfgdfg","src":"https://s3.vn-hcm-1.vietnix.cloud/cuontruyen/imports/cao-vo-ha-canh-en-mot-van-nam-sau-893sqz/chuong-192-206/006.webp","storageKey":"https://s3.vn-hcm-1.vietnix.cloud/cuontruyen/imports/cao-vo-ha-canh-en-mot-van-nam-sau-893sqz/chuong-192-206/006.webp","width":720,"height":6774,"originalBytes":638259,"storedBytes":455180,"optimized":true,"order":5,"imageUrl":"https://s3.vn-hcm-1.vietnix.cloud/cuontruyen/imports/cao-vo-ha-canh-en-mot-van-nam-sau-893sqz/chuong-192-206/006.webp"},{"index":6,"sourceUrl":"https://s135.hinhhinh.com/13646/192/6.jpg?gt=hdfgdfg","src":"https://s3.vn-hcm-1.vietnix.cloud/cuontruyen/imports/cao-vo-ha-canh-en-mot-van-nam-sau-893sqz/chuong-192-206/007.webp","storageKey":"https://s3.vn-hcm-1.vietnix.cloud/cuontruyen/imports/cao-vo-ha-canh-en-mot-van-nam-sau-893sqz/chuong-192-206/007.webp","width":720,"height":6774,"originalBytes":694130,"storedBytes":501946,"optimized":true,"order":6,"imageUrl":"https://s3.vn-hcm-1.vietnix.cloud/cuontruyen/imports/cao-vo-ha-canh-en-mot-van-nam-sau-893sqz/chuong-192-206/007.webp"},{"index":7,"sourceUrl":"https://s135.hinhhinh.com/13646/192/7.jpg?gt=hdfgdfg","src":"https://s3.vn-hcm-1.vietnix.cloud/cuontruyen/imports/cao-vo-ha-canh-en-mot-van-nam-sau-893sqz/chuong-192-206/008.webp","storageKey":"https://s3.vn-hcm-1.vietnix.cloud/cuontruyen/imports/cao-vo-ha-canh-en-mot-van-nam-sau-893sqz/chuong-192-206/008.webp","width":720,"height":6774,"originalBytes":630292,"storedBytes":456230,"optimized":true,"order":7,"imageUrl":"https://s3.vn-hcm-1.vietnix.cloud/cuontruyen/imports/cao-vo-ha-canh-en-mot-van-nam-sau-893sqz/chuong-192-206/008.webp"},{"index":8,"sourceUrl":"https://s135.hinhhinh.com/13646/192/8.jpg?gt=hdfgdfg","src":"https://s3.vn-hcm-1.vietnix.cloud/cuontruyen/imports/cao-vo-ha-canh-en-mot-van-nam-sau-893sqz/chuong-192-206/009.webp","storageKey":"https://s3.vn-hcm-1.vietnix.cloud/cuontruyen/imports/cao-vo-ha-canh-en-mot-van-nam-sau-893sqz/chuong-192-206/009.webp","width":720,"height":6774,"originalBytes":599899,"storedBytes":425706,"optimized":true,"order":8,"imageUrl":"https://s3.vn-hcm-1.vietnix.cloud/cuontruyen/imports/cao-vo-ha-canh-en-mot-van-nam-sau-893sqz/chuong-192-206/009.webp"},{"index":9,"sourceUrl":"https://s135.hinhhinh.com/13646/192/9.jpg?gt=hdfgdfg","src":"https://s3.vn-hcm-1.vietnix.cloud/cuontruyen/imports/cao-vo-ha-canh-en-mot-van-nam-sau-893sqz/chuong-192-206/010.webp","storageKey":"https://s3.vn-hcm-1.vietnix.cloud/cuontruyen/imports/cao-vo-ha-canh-en-mot-van-nam-sau-893sqz/chuong-192-206/010.webp","width":720,"height":6774,"originalBytes":610250,"storedBytes":442892,"optimized":true,"order":9,"imageUrl":"https://s3.vn-hcm-1.vietnix.cloud/cuontruyen/imports/cao-vo-ha-canh-en-mot-van-nam-sau-893sqz/chuong-192-206/010.webp"},{"index":10,"sourceUrl":"https://s135.hinhhinh.com/13646/192/10.jpg?gt=hdfgdfg","src":"https://s3.vn-hcm-1.vietnix.cloud/cuontruyen/imports/cao-vo-ha-canh-en-mot-van-nam-sau-893sqz/chuong-192-206/011.webp","storageKey":"https://s3.vn-hcm-1.vietnix.cloud/cuontruyen/imports/cao-vo-ha-canh-en-mot-van-nam-sau-893sqz/chuong-192-206/011.webp","width":720,"height":6774,"originalBytes":609398,"storedBytes":447918,"optimized":true,"order":10,"imageUrl":"https://s3.vn-hcm-1.vietnix.cloud/cuontruyen/imports/cao-vo-ha-canh-en-mot-van-nam-sau-893sqz/chuong-192-206/011.webp"},{"index":11,"sourceUrl":"https://s135.hinhhinh.com/13646/192/11.jpg?gt=hdfgdfg","src":"https://s3.vn-hcm-1.vietnix.cloud/cuontruyen/imports/cao-vo-ha-canh-en-mot-van-nam-sau-893sqz/chuong-192-206/012.webp","storageKey":"https://s3.vn-hcm-1.vietnix.cloud/cuontruyen/imports/cao-vo-ha-canh-en-mot-van-nam-sau-893sqz/chuong-192-206/012.webp","width":720,"height":6774,"originalBytes":565238,"storedBytes":409166,"optimized":true,"order":11,"imageUrl":"https://s3.vn-hcm-1.vietnix.cloud/cuontruyen/imports/cao-vo-ha-canh-en-mot-van-nam-sau-893sqz/chuong-192-206/012.webp"},{"index":12,"sourceUrl":"https://s135.hinhhinh.com/13646/192/12.jpg?gt=hdfgdfg","src":"https://s3.vn-hcm-1.vietnix.cloud/cuontruyen/imports/cao-vo-ha-canh-en-mot-van-nam-sau-893sqz/chuong-192-206/013.webp","storageKey":"https://s3.vn-hcm-1.vietnix.cloud/cuontruyen/imports/cao-vo-ha-canh-en-mot-van-nam-sau-893sqz/chuong-192-206/013.webp","width":720,"height":6774,"originalBytes":509063,"storedBytes":346604,"optimized":true,"order":12,"imageUrl":"https://s3.vn-hcm-1.vietnix.cloud/cuontruyen/imports/cao-vo-ha-canh-en-mot-van-nam-sau-893sqz/chuong-192-206/013.webp"},{"index":13,"sourceUrl":"https://s135.hinhhinh.com/13646/192/13.jpg?gt=hdfgdfg","src":"https://s3.vn-hcm-1.vietnix.cloud/cuontruyen/imports/cao-vo-ha-canh-en-mot-van-nam-sau-893sqz/chuong-192-206/014.webp","storageKey":"https://s3.vn-hcm-1.vietnix.cloud/cuontruyen/imports/cao-vo-ha-canh-en-mot-van-nam-sau-893sqz/chuong-192-206/014.webp","width":720,"height":6774,"originalBytes":605099,"storedBytes":449278,"optimized":true,"order":13,"imageUrl":"https://s3.vn-hcm-1.vietnix.cloud/cuontruyen/imports/cao-vo-ha-canh-en-mot-van-nam-sau-893sqz/chuong-192-206/014.webp"},{"index":14,"sourceUrl":"https://s135.hinhhinh.com/13646/192/14.jpg?gt=hdfgdfg","src":"https://s3.vn-hcm-1.vietnix.cloud/cuontruyen/imports/cao-vo-ha-canh-en-mot-van-nam-sau-893sqz/chuong-192-206/015.webp","storageKey":"https://s3.vn-hcm-1.vietnix.cloud/cuontruyen/imports/cao-vo-ha-canh-en-mot-van-nam-sau-893sqz/chuong-192-206/015.webp","width":720,"height":6774,"originalBytes":610507,"storedBytes":443422,"optimized":true,"order":14,"imageUrl":"https://s3.vn-hcm-1.vietnix.cloud/cuontruyen/imports/cao-vo-ha-canh-en-mot-van-nam-sau-893sqz/chuong-192-206/015.webp"},{"index":15,"sourceUrl":"https://s135.hinhhinh.com/13646/192/15.jpg?gt=hdfgdfg","src":"https://s3.vn-hcm-1.vietnix.cloud/cuontruyen/imports/cao-vo-ha-canh-en-mot-van-nam-sau-893sqz/chuong-192-206/016.webp","storageKey":"https://s3.vn-hcm-1.vietnix.cloud/cuontruyen/imports/cao-vo-ha-canh-en-mot-van-nam-sau-893sqz/chuong-192-206/016.webp","width":720,"height":6774,"originalBytes":512376,"storedBytes":351330,"optimized":true,"order":15,"imageUrl":"https://s3.vn-hcm-1.vietnix.cloud/cuontruyen/imports/cao-vo-ha-canh-en-mot-van-nam-sau-893sqz/chuong-192-206/016.webp"},{"index":16,"sourceUrl":"https://s135.hinhhinh.com/13646/192/16.jpg?gt=hdfgdfg","src":"https://s3.vn-hcm-1.vietnix.cloud/cuontruyen/imports/cao-vo-ha-canh-en-mot-van-nam-sau-893sqz/chuong-192-206/017.webp","storageKey":"https://s3.vn-hcm-1.vietnix.cloud/cuontruyen/imports/cao-vo-ha-canh-en-mot-van-nam-sau-893sqz/chuong-192-206/017.webp","width":720,"height":6774,"originalBytes":564440,"storedBytes":393484,"optimized":true,"order":16,"imageUrl":"https://s3.vn-hcm-1.vietnix.cloud/cuontruyen/imports/cao-vo-ha-canh-en-mot-van-nam-sau-893sqz/chuong-192-206/017.webp"},{"index":17,"sourceUrl":"https://s135.hinhhinh.com/13646/192/17.jpg?gt=hdfgdfg","src":"https://s3.vn-hcm-1.vietnix.cloud/cuontruyen/imports/cao-vo-ha-canh-en-mot-van-nam-sau-893sqz/chuong-192-206/018.webp","storageKey":"https://s3.vn-hcm-1.vietnix.cloud/cuontruyen/imports/cao-vo-ha-canh-en-mot-van-nam-sau-893sqz/chuong-192-206/018.webp","width":720,"height":3352,"originalBytes":219110,"storedBytes":148198,"optimized":true,"order":17,"imageUrl":"https://s3.vn-hcm-1.vietnix.cloud/cuontruyen/imports/cao-vo-ha-canh-en-mot-van-nam-sau-893sqz/chuong-192-206/018.webp"},{"index":18,"sourceUrl":"https://s135.hinhhinh.com/13646/192/18.jpg?gt=hdfgdfg","src":"https://s3.vn-hcm-1.vietnix.cloud/cuontruyen/imports/cao-vo-ha-canh-en-mot-van-nam-sau-893sqz/chuong-192-206/019.jpg","storageKey":"https://s3.vn-hcm-1.vietnix.cloud/cuontruyen/imports/cao-vo-ha-canh-en-mot-van-nam-sau-893sqz/chuong-192-206/019.jpg","width":null,"height":null,"originalBytes":74309,"storedBytes":74309,"optimized":false,"order":18,"imageUrl":"https://s3.vn-hcm-1.vietnix.cloud/cuontruyen/imports/cao-vo-ha-canh-en-mot-van-nam-sau-893sqz/chuong-192-206/019.jpg"},{"index":19,"sourceUrl":"https://s135.hinhhinh.com/13646/192/19.jpg?gt=hdfgdfg","src":"https://s3.vn-hcm-1.vietnix.cloud/cuontruyen/imports/cao-vo-ha-canh-en-mot-van-nam-sau-893sqz/chuong-192-206/020.webp","storageKey":"https://s3.vn-hcm-1.vietnix.cloud/cuontruyen/imports/cao-vo-ha-canh-en-mot-van-nam-sau-893sqz/chuong-192-206/020.webp","width":900,"height":1061,"originalBytes":349232,"storedBytes":166106,"optimized":true,"order":19,"imageUrl":"https://s3.vn-hcm-1.vietnix.cloud/cuontruyen/imports/cao-vo-ha-canh-en-mot-van-nam-sau-893sqz/chuong-192-206/020.webp"}]}],"previousChapter":{"id":"chuong-191-205","title":"Chương 191","label":"Chương 191","slug":"chuong-191","status":"public","imported":true,"pageCount":6,"sourceOrder":204},"nextChapter":{"id":"chuong-193-207","title":"Chương 193","label":"Chương 193","slug":"chuong-193","status":"public","imported":true,"pageCount":149,"sourceOrder":206}}
